sqlalchemy_vertica/__init__.py
sqlalchemy_vertica/base.py
sqlalchemy_vertica/dialect_pyodbc.py
sqlalchemy_vertica/dialect_vertica_python.py
sqlalchemy_vertica-0.0.5.dist-info/LICENSE
sqlalchemy_vertica-0.0.5.dist-info/METADATA
sqlalchemy_vertica-0.0.5.dist-info/WHEEL
sqlalchemy_vertica-0.0.5.dist-info/entry_points.txt
sqlalchemy_vertica-0.0.5.dist-info/top_level.txt
sqlalchemy_vertica-0.0.5.dist-info/RECORD
