Metadata-Version: 2.1
Name: sqlalchemy-vertica
Version: 0.0.5
Summary: Vertica dialect for sqlalchemy
Home-page: https://github.com/lv10/sqlalchemy-vertica
Author: Luis Villamarin
Author-email: luis@lv10.me
License: MIT
Download-URL: https://github.com/lv10/sqlalchemy-vertica/tarball/0.0.5
Platform: UNKNOWN
Requires-Dist: six (>=1.10.0)
Requires-Dist: sqlalchemy (>=1.1.11)
Provides-Extra: pyodbc
Requires-Dist: pyodbc (>=4.0.16) ; extra == 'pyodbc'
Provides-Extra: vertica-python
Requires-Dist: vertica-python (>=0.7.3) ; extra == 'vertica-python'
